helpful.py
setup.py
helpful.egg-info/PKG-INFO
helpful.egg-info/SOURCES.txt
helpful.egg-info/dependency_links.txt
helpful.egg-info/requires.txt
helpful.egg-info/top_level.txt