Metadata-Version: 1.1
Name: helpful
Version: 0.8.1
Summary: Helpful tools for Python
Home-page: https://github.com/imsofly/python-helpful
Author: Cal Leeming
Author-email: cal@iops.io
License: UNKNOWN
Keywords: helpful,useful
Platform: UNKNOWN
Classifier: Programming Language :: Python :: 2.7
Classifier: Programming Language :: Python :: 3.4
